twat_llm/__version__.py
twat_llm/twat_llm.py
twat_llm-2.7.5.dist-info/METADATA
twat_llm-2.7.5.dist-info/WHEEL
twat_llm-2.7.5.dist-info/licenses/LICENSE
twat_llm-2.7.5.dist-info/RECORD
